odoo/addons/shopinvader_customer_price/README.rst
odoo/addons/shopinvader_customer_price/__init__.py
odoo/addons/shopinvader_customer_price/__manifest__.py
odoo/addons/shopinvader_customer_price/i18n/shopinvader_customer_price.pot
odoo/addons/shopinvader_customer_price/models/__init__.py
odoo/addons/shopinvader_customer_price/models/shopinvader_backend.py
odoo/addons/shopinvader_customer_price/readme/CONTRIBUTORS.rst
odoo/addons/shopinvader_customer_price/readme/CREDITS.rst
odoo/addons/shopinvader_customer_price/readme/DESCRIPTION.rst
odoo/addons/shopinvader_customer_price/readme/ROADMAP.rst
odoo/addons/shopinvader_customer_price/services/__init__.py
odoo/addons/shopinvader_customer_price/services/customer_price.py
odoo/addons/shopinvader_customer_price/static/description/index.html
odoo/addons/shopinvader_customer_price/tests/__init__.py
odoo/addons/shopinvader_customer_price/tests/test_cart.py
odoo/addons/shopinvader_customer_price/tests/test_customer_price.py
odoo/addons/shopinvader_customer_price/views/shopinvader_backend_views.xml
odoo14_addon_shopinvader_customer_price-14.0.1.0.2.dist-info/METADATA
odoo14_addon_shopinvader_customer_price-14.0.1.0.2.dist-info/WHEEL
odoo14_addon_shopinvader_customer_price-14.0.1.0.2.dist-info/top_level.txt
odoo14_addon_shopinvader_customer_price-14.0.1.0.2.dist-info/RECORD
